{"products":[{"id":689514,"name":"09112894175","productVariantId":686612,"slug":"09112894175","thumbnailUrl":null,"price":1668000.0,"priceWithTax":1732000,"discountPrice":1000000,"discountPercentage":40.0,"productStatus":"ACTIVE","productType":"EMERALD","attributes":[{"icon":null,"locationKey":null,"title":"Sku Code","attributeValueVms":[{"value":"MCCIMobNum","displayText":"MCCIMobNum"}],"shortcut":false},{"icon":null,"locationKey":null,"title":"whId","attributeValueVms":[{"value":"10585201080747021","displayText":"10585201080747021"}],"shortcut":false},{"icon":null,"locationKey":"L1","title":"دائمی یا اعتباری","attributeValueVms":[{"value":"POSTPAID","displayText":"دائمی"}],"shortcut":false},{"icon":null,"locationKey":null,"title":"Item Type Id","attributeValueVms":[{"value":"3004","displayText":"3004"}],"shortcut":false},{"icon":null,"locationKey":"L2","title":"نوع سیم‌کارت","attributeValueVms":[{"value":"EMERALD","displayText":"زمردی"}],"shortcut":false},{"icon":null,"locationKey":null,"title":"هدیه اینترنت","attributeValueVms":[{"value":"بین 5 تا 30 گیگابایت","displayText":"بین 5 تا 30 گیگابایت"}],"shortcut":false},{"icon":null,"locationKey":null,"title":"قیمت","attributeValueVms":[{"value":"1668000","displayText":"1668000"}],"shortcut":false},{"icon":"mail","locationKey":"L9","title":"پیامک","attributeValueVms":[{"value":"600 پیامک | 6 ماهه (100 پیامک هر ماه)","displayText":"600 پیامک | 6 ماهه (100 پیامک هر ماه)"}],"shortcut":false},{"icon":null,"locationKey":null,"title":"الگوی شماره","attributeValueVms":[{"value":"NORMAL","displayText":"معمولی (سایر سیم‌کارت‌ها)"}],"shortcut":false},{"icon":"phone","locationKey":"L4","title":"مکالمه","attributeValueVms":[{"value":"٪۵۰ تخفیف ماهیانه مکالمه درون شبکه |به مدت 6 ماه","displayText":"٪۵۰ تخفیف ماهیانه مکالمه درون شبکه |به مدت 6 ماه"}],"shortcut":false},{"icon":null,"locationKey":null,"title":"offerId","attributeValueVms":[{"value":"144","displayText":"144"}],"shortcut":false},{"icon":"globe","locationKey":"L3","title":"اینترنت","attributeValueVms":[{"value":"30 گیگابایت | 1 ماهه ","displayText":"30 گیگابایت | 1 ماهه "}],"shortcut":false}],"createdOn":"2025-09-09T21:31:10.435"},{"id":689293,"name":"09112895348","productVariantId":686196,"slug":"09112895348","thumbnailUrl":null,"price":1668000.0,"priceWithTax":1732000,"discountPrice":1000000,"discountPercentage":40.0,"productStatus":"ACTIVE","productType":"EMERALD","attributes":[{"icon":null,"locationKey":null,"title":"Sku Code","attributeValueVms":[{"value":"MCCIMobNum","displayText":"MCCIMobNum"}],"shortcut":false},{"icon":null,"locationKey":"L1","title":"دائمی یا اعتباری","attributeValueVms":[{"value":"POSTPAID","displayText":"دائمی"}],"shortcut":false},{"icon":null,"locationKey":null,"title":"whId","attributeValueVms":[{"value":"10585201080747021","displayText":"10585201080747021"}],"shortcut":false},{"icon":null,"locationKey":null,"title":"Item Type Id","attributeValueVms":[{"value":"3004","displayText":"3004"}],"shortcut":false},{"icon":null,"locationKey":null,"title":"الگوی شماره","attributeValueVms":[{"value":"NORMAL","displayText":"معمولی (سایر سیم‌کارت‌ها)"}],"shortcut":false},{"icon":"mail","locationKey":"L9","title":"پیامک","attributeValueVms":[{"value":"600 پیامک | 6 ماهه (100 پیامک هر ماه)","displayText":"600 پیامک | 6 ماهه (100 پیامک هر ماه)"}],"shortcut":false},{"icon":"phone","locationKey":"L4","title":"مکالمه","attributeValueVms":[{"value":"٪۵۰ تخفیف ماهیانه مکالمه درون شبکه |به مدت 6 ماه","displayText":"٪۵۰ تخفیف ماهیانه مکالمه درون شبکه |به مدت 6 ماه"}],"shortcut":false},{"icon":null,"locationKey":null,"title":"قیمت","attributeValueVms":[{"value":"1668000","displayText":"1668000"}],"shortcut":false},{"icon":null,"locationKey":null,"title":"هدیه اینترنت","attributeValueVms":[{"value":"بین 5 تا 30 گیگابایت","displayText":"بین 5 تا 30 گیگابایت"}],"shortcut":false},{"icon":null,"locationKey":"L2","title":"نوع سیم‌کارت","attributeValueVms":[{"value":"EMERALD","displayText":"زمردی"}],"shortcut":false},{"icon":null,"locationKey":null,"title":"offerId","attributeValueVms":[{"value":"144","displayText":"144"}],"shortcut":false},{"icon":"globe","locationKey":"L3","title":"اینترنت","attributeValueVms":[{"value":"30 گیگابایت | 1 ماهه ","displayText":"30 گیگابایت | 1 ماهه "}],"shortcut":false}],"createdOn":"2025-09-09T21:31:10.014"},{"id":689175,"name":"09112671293","productVariantId":686172,"slug":"09112671293","thumbnailUrl":null,"price":1668000.0,"priceWithTax":1732000,"discountPrice":1000000,"discountPercentage":40.0,"productStatus":"ACTIVE","productType":"EMERALD","attributes":[{"icon":null,"locationKey":null,"title":"Sku Code","attributeValueVms":[{"value":"MCCIMobNum","displayText":"MCCIMobNum"}],"shortcut":false},{"icon":null,"locationKey":null,"title":"whId","attributeValueVms":[{"value":"10585201080747021","displayText":"10585201080747021"}],"shortcut":false},{"icon":null,"locationKey":"L1","title":"دائمی یا اعتباری","attributeValueVms":[{"value":"POSTPAID","displayText":"دائمی"}],"shortcut":false},{"icon":null,"locationKey":null,"title":"Item Type Id","attributeValueVms":[{"value":"3004","displayText":"3004"}],"shortcut":false},{"icon":null,"locationKey":"L2","title":"نوع سیم‌کارت","attributeValueVms":[{"value":"EMERALD","displayText":"زمردی"}],"shortcut":false},{"icon":null,"locationKey":null,"title":"هدیه اینترنت","attributeValueVms":[{"value":"بین 5 تا 30 گیگابایت","displayText":"بین 5 تا 30 گیگابایت"}],"shortcut":false},{"icon":null,"locationKey":null,"title":"الگوی شماره","attributeValueVms":[{"value":"NORMAL","displayText":"معمولی (سایر سیم‌کارت‌ها)"}],"shortcut":false},{"icon":null,"locationKey":null,"title":"قیمت","attributeValueVms":[{"value":"1668000","displayText":"1668000"}],"shortcut":false},{"icon":"mail","locationKey":"L9","title":"پیامک","attributeValueVms":[{"value":"600 پیامک | 6 ماهه (100 پیامک هر ماه)","displayText":"600 پیامک | 6 ماهه (100 پیامک هر ماه)"}],"shortcut":false},{"icon":"phone","locationKey":"L4","title":"مکالمه","attributeValueVms":[{"value":"٪۵۰ تخفیف ماهیانه مکالمه درون شبکه |به مدت 6 ماه","displayText":"٪۵۰ تخفیف ماهیانه مکالمه درون شبکه |به مدت 6 ماه"}],"shortcut":false},{"icon":null,"locationKey":null,"title":"offerId","attributeValueVms":[{"value":"144","displayText":"144"}],"shortcut":false},{"icon":"globe","locationKey":"L3","title":"اینترنت","attributeValueVms":[{"value":"30 گیگابایت | 1 ماهه ","displayText":"30 گیگابایت | 1 ماهه "}],"shortcut":false}],"createdOn":"2025-09-09T21:31:09.727"},{"id":689248,"name":"09112893614","productVariantId":686511,"slug":"09112893614","thumbnailUrl":null,"price":1668000.0,"priceWithTax":1732000,"discountPrice":1000000,"discountPercentage":40.0,"productStatus":"ACTIVE","productType":"EMERALD","attributes":[{"icon":null,"locationKey":null,"title":"Sku Code","attributeValueVms":[{"value":"MCCIMobNum","displayText":"MCCIMobNum"}],"shortcut":false},{"icon":null,"locationKey":"L1","title":"دائمی یا اعتباری","attributeValueVms":[{"value":"POSTPAID","displayText":"دائمی"}],"shortcut":false},{"icon":null,"locationKey":null,"title":"whId","attributeValueVms":[{"value":"10585201080747021","displayText":"10585201080747021"}],"shortcut":false},{"icon":null,"locationKey":null,"title":"Item Type Id","attributeValueVms":[{"value":"3004","displayText":"3004"}],"shortcut":false},{"icon":null,"locationKey":null,"title":"قیمت","attributeValueVms":[{"value":"1668000","displayText":"1668000"}],"shortcut":false},{"icon":null,"locationKey":null,"title":"الگوی شماره","attributeValueVms":[{"value":"NORMAL","displayText":"معمولی (سایر سیم‌کارت‌ها)"}],"shortcut":false},{"icon":"mail","locationKey":"L9","title":"پیامک","attributeValueVms":[{"value":"600 پیامک | 6 ماهه (100 پیامک هر ماه)","displayText":"600 پیامک | 6 ماهه (100 پیامک هر ماه)"}],"shortcut":false},{"icon":"phone","locationKey":"L4","title":"مکالمه","attributeValueVms":[{"value":"٪۵۰ تخفیف ماهیانه مکالمه درون شبکه |به مدت 6 ماه","displayText":"٪۵۰ تخفیف ماهیانه مکالمه درون شبکه |به مدت 6 ماه"}],"shortcut":false},{"icon":null,"locationKey":null,"title":"offerId","attributeValueVms":[{"value":"144","displayText":"144"}],"shortcut":false},{"icon":null,"locationKey":null,"title":"هدیه اینترنت","attributeValueVms":[{"value":"بین 5 تا 30 گیگابایت","displayText":"بین 5 تا 30 گیگابایت"}],"shortcut":false},{"icon":"globe","locationKey":"L3","title":"اینترنت","attributeValueVms":[{"value":"30 گیگابایت | 1 ماهه ","displayText":"30 گیگابایت | 1 ماهه "}],"shortcut":false},{"icon":null,"locationKey":"L2","title":"نوع سیم‌کارت","attributeValueVms":[{"value":"EMERALD","displayText":"زمردی"}],"shortcut":false}],"createdOn":"2025-09-09T21:31:09.898"},{"id":689817,"name":"09112652176","productVariantId":686483,"slug":"09112652176","thumbnailUrl":null,"price":1668000.0,"priceWithTax":1732000,"discountPrice":1000000,"discountPercentage":40.0,"productStatus":"ACTIVE","productType":"EMERALD","attributes":[{"icon":null,"locationKey":null,"title":"Sku Code","attributeValueVms":[{"value":"MCCIMobNum","displayText":"MCCIMobNum"}],"shortcut":false},{"icon":null,"locationKey":"L1","title":"دائمی یا اعتباری","attributeValueVms":[{"value":"POSTPAID","displayText":"دائمی"}],"shortcut":false},{"icon":null,"locationKey":null,"title":"whId","attributeValueVms":[{"value":"10585201080747021","displayText":"10585201080747021"}],"shortcut":false},{"icon":null,"locationKey":null,"title":"Item Type Id","attributeValueVms":[{"value":"3004","displayText":"3004"}],"shortcut":false},{"icon":"mail","locationKey":"L9","title":"پیامک","attributeValueVms":[{"value":"600 پیامک | 6 ماهه (100 پیامک هر ماه)","displayText":"600 پیامک | 6 ماهه (100 پیامک هر ماه)"}],"shortcut":false},{"icon":null,"locationKey":null,"title":"هدیه اینترنت","attributeValueVms":[{"value":"بین 5 تا 30 گیگابایت","displayText":"بین 5 تا 30 گیگابایت"}],"shortcut":false},{"icon":"phone","locationKey":"L4","title":"مکالمه","attributeValueVms":[{"value":"٪۵۰ تخفیف ماهیانه مکالمه درون شبکه |به مدت 6 ماه","displayText":"٪۵۰ تخفیف ماهیانه مکالمه درون شبکه |به مدت 6 ماه"}],"shortcut":false},{"icon":null,"locationKey":null,"title":"قیمت","attributeValueVms":[{"value":"1668000","displayText":"1668000"}],"shortcut":false},{"icon":null,"locationKey":null,"title":"offerId","attributeValueVms":[{"value":"144","displayText":"144"}],"shortcut":false},{"icon":"globe","locationKey":"L3","title":"اینترنت","attributeValueVms":[{"value":"30 گیگابایت | 1 ماهه ","displayText":"30 گیگابایت | 1 ماهه "}],"shortcut":false},{"icon":null,"locationKey":null,"title":"الگوی شماره","attributeValueVms":[{"value":"NORMAL","displayText":"معمولی (سایر سیم‌کارت‌ها)"}],"shortcut":false},{"icon":null,"locationKey":"L2","title":"نوع سیم‌کارت","attributeValueVms":[{"value":"EMERALD","displayText":"زمردی"}],"shortcut":false}],"createdOn":"2025-09-09T21:31:11.127"},{"id":689985,"name":"09112892361","productVariantId":686160,"slug":"09112892361","thumbnailUrl":null,"price":1668000.0,"priceWithTax":1732000,"discountPrice":1000000,"discountPercentage":40.0,"productStatus":"ACTIVE","productType":"EMERALD","attributes":[{"icon":null,"locationKey":null,"title":"Sku Code","attributeValueVms":[{"value":"MCCIMobNum","displayText":"MCCIMobNum"}],"shortcut":false},{"icon":null,"locationKey":"L1","title":"دائمی یا اعتباری","attributeValueVms":[{"value":"POSTPAID","displayText":"دائمی"}],"shortcut":false},{"icon":null,"locationKey":null,"title":"whId","attributeValueVms":[{"value":"10585201080747021","displayText":"10585201080747021"}],"shortcut":false},{"icon":null,"locationKey":null,"title":"Item Type Id","attributeValueVms":[{"value":"3004","displayText":"3004"}],"shortcut":false},{"icon":null,"locationKey":null,"title":"الگوی شماره","attributeValueVms":[{"value":"NORMAL","displayText":"معمولی (سایر سیم‌کارت‌ها)"}],"shortcut":false},{"icon":"mail","locationKey":"L9","title":"پیامک","attributeValueVms":[{"value":"600 پیامک | 6 ماهه (100 پیامک هر ماه)","displayText":"600 پیامک | 6 ماهه (100 پیامک هر ماه)"}],"shortcut":false},{"icon":"phone","locationKey":"L4","title":"مکالمه","attributeValueVms":[{"value":"٪۵۰ تخفیف ماهیانه مکالمه درون شبکه |به مدت 6 ماه","displayText":"٪۵۰ تخفیف ماهیانه مکالمه درون شبکه |به مدت 6 ماه"}],"shortcut":false},{"icon":null,"locationKey":null,"title":"قیمت","attributeValueVms":[{"value":"1668000","displayText":"1668000"}],"shortcut":false},{"icon":null,"locationKey":null,"title":"offerId","attributeValueVms":[{"value":"144","displayText":"144"}],"shortcut":false},{"icon":"globe","locationKey":"L3","title":"اینترنت","attributeValueVms":[{"value":"30 گیگابایت | 1 ماهه ","displayText":"30 گیگابایت | 1 ماهه "}],"shortcut":false},{"icon":null,"locationKey":"L2","title":"نوع سیم‌کارت","attributeValueVms":[{"value":"EMERALD","displayText":"زمردی"}],"shortcut":false},{"icon":null,"locationKey":null,"title":"هدیه اینترنت","attributeValueVms":[{"value":"بین 5 تا 30 گیگابایت","displayText":"بین 5 تا 30 گیگابایت"}],"shortcut":false}],"createdOn":"2025-09-09T21:31:11.492"},{"id":689403,"name":"09112638945","productVariantId":686430,"slug":"09112638945","thumbnailUrl":null,"price":1668000.0,"priceWithTax":1732000,"discountPrice":1000000,"discountPercentage":40.0,"productStatus":"ACTIVE","productType":"EMERALD","attributes":[{"icon":null,"locationKey":null,"title":"Sku Code","attributeValueVms":[{"value":"MCCIMobNum","displayText":"MCCIMobNum"}],"shortcut":false},{"icon":null,"locationKey":null,"title":"whId","attributeValueVms":[{"value":"10585201080747021","displayText":"10585201080747021"}],"shortcut":false},{"icon":null,"locationKey":null,"title":"Item Type Id","attributeValueVms":[{"value":"3004","displayText":"3004"}],"shortcut":false},{"icon":null,"locationKey":"L1","title":"دائمی یا اعتباری","attributeValueVms":[{"value":"POSTPAID","displayText":"دائمی"}],"shortcut":false},{"icon":null,"locationKey":null,"title":"الگوی شماره","attributeValueVms":[{"value":"NORMAL","displayText":"معمولی (سایر سیم‌کارت‌ها)"}],"shortcut":false},{"icon":null,"locationKey":null,"title":"هدیه اینترنت","attributeValueVms":[{"value":"بین 5 تا 30 گیگابایت","displayText":"بین 5 تا 30 گیگابایت"}],"shortcut":false},{"icon":null,"locationKey":null,"title":"قیمت","attributeValueVms":[{"value":"1668000","displayText":"1668000"}],"shortcut":false},{"icon":null,"locationKey":"L2","title":"نوع سیم‌کارت","attributeValueVms":[{"value":"EMERALD","displayText":"زمردی"}],"shortcut":false},{"icon":"mail","locationKey":"L9","title":"پیامک","attributeValueVms":[{"value":"600 پیامک | 6 ماهه (100 پیامک هر ماه)","displayText":"600 پیامک | 6 ماهه (100 پیامک هر ماه)"}],"shortcut":false},{"icon":"phone","locationKey":"L4","title":"مکالمه","attributeValueVms":[{"value":"٪۵۰ تخفیف ماهیانه مکالمه درون شبکه |به مدت 6 ماه","displayText":"٪۵۰ تخفیف ماهیانه مکالمه درون شبکه |به مدت 6 ماه"}],"shortcut":false},{"icon":null,"locationKey":null,"title":"offerId","attributeValueVms":[{"value":"144","displayText":"144"}],"shortcut":false},{"icon":"globe","locationKey":"L3","title":"اینترنت","attributeValueVms":[{"value":"30 گیگابایت | 1 ماهه ","displayText":"30 گیگابایت | 1 ماهه "}],"shortcut":false}],"createdOn":"2025-09-09T21:31:10.243"},{"id":689684,"name":"09112894834","productVariantId":686482,"slug":"09112894834","thumbnailUrl":null,"price":1668000.0,"priceWithTax":1732000,"discountPrice":1000000,"discountPercentage":40.0,"productStatus":"ACTIVE","productType":"EMERALD","attributes":[{"icon":null,"locationKey":null,"title":"Sku Code","attributeValueVms":[{"value":"MCCIMobNum","displayText":"MCCIMobNum"}],"shortcut":false},{"icon":null,"locationKey":null,"title":"whId","attributeValueVms":[{"value":"10585201080747021","displayText":"10585201080747021"}],"shortcut":false},{"icon":null,"locationKey":"L1","title":"دائمی یا اعتباری","attributeValueVms":[{"value":"POSTPAID","displayText":"دائمی"}],"shortcut":false},{"icon":null,"locationKey":null,"title":"Item Type Id","attributeValueVms":[{"value":"3004","displayText":"3004"}],"shortcut":false},{"icon":null,"locationKey":null,"title":"قیمت","attributeValueVms":[{"value":"1668000","displayText":"1668000"}],"shortcut":false},{"icon":null,"locationKey":null,"title":"هدیه اینترنت","attributeValueVms":[{"value":"بین 5 تا 30 گیگابایت","displayText":"بین 5 تا 30 گیگابایت"}],"shortcut":false},{"icon":null,"locationKey":"L2","title":"نوع سیم‌کارت","attributeValueVms":[{"value":"EMERALD","displayText":"زمردی"}],"shortcut":false},{"icon":"mail","locationKey":"L9","title":"پیامک","attributeValueVms":[{"value":"600 پیامک | 6 ماهه (100 پیامک هر ماه)","displayText":"600 پیامک | 6 ماهه (100 پیامک هر ماه)"}],"shortcut":false},{"icon":"phone","locationKey":"L4","title":"مکالمه","attributeValueVms":[{"value":"٪۵۰ تخفیف ماهیانه مکالمه درون شبکه |به مدت 6 ماه","displayText":"٪۵۰ تخفیف ماهیانه مکالمه درون شبکه |به مدت 6 ماه"}],"shortcut":false},{"icon":null,"locationKey":null,"title":"الگوی شماره","attributeValueVms":[{"value":"NORMAL","displayText":"معمولی (سایر سیم‌کارت‌ها)"}],"shortcut":false},{"icon":null,"locationKey":null,"title":"offerId","attributeValueVms":[{"value":"144","displayText":"144"}],"shortcut":false},{"icon":"globe","locationKey":"L3","title":"اینترنت","attributeValueVms":[{"value":"30 گیگابایت | 1 ماهه ","displayText":"30 گیگابایت | 1 ماهه "}],"shortcut":false}],"createdOn":"2025-09-09T21:31:10.799"},{"id":689555,"name":"09112679548","productVariantId":686315,"slug":"09112679548","thumbnailUrl":null,"price":1668000.0,"priceWithTax":1732000,"discountPrice":1000000,"discountPercentage":40.0,"productStatus":"ACTIVE","productType":"EMERALD","attributes":[{"icon":null,"locationKey":null,"title":"Sku Code","attributeValueVms":[{"value":"MCCIMobNum","displayText":"MCCIMobNum"}],"shortcut":false},{"icon":null,"locationKey":null,"title":"whId","attributeValueVms":[{"value":"10585201080747021","displayText":"10585201080747021"}],"shortcut":false},{"icon":null,"locationKey":"L1","title":"دائمی یا اعتباری","attributeValueVms":[{"value":"POSTPAID","displayText":"دائمی"}],"shortcut":false},{"icon":null,"locationKey":null,"title":"Item Type Id","attributeValueVms":[{"value":"3004","displayText":"3004"}],"shortcut":false},{"icon":null,"locationKey":null,"title":"قیمت","attributeValueVms":[{"value":"1668000","displayText":"1668000"}],"shortcut":false},{"icon":null,"locationKey":null,"title":"هدیه اینترنت","attributeValueVms":[{"value":"بین 5 تا 30 گیگابایت","displayText":"بین 5 تا 30 گیگابایت"}],"shortcut":false},{"icon":null,"locationKey":"L2","title":"نوع سیم‌کارت","attributeValueVms":[{"value":"EMERALD","displayText":"زمردی"}],"shortcut":false},{"icon":"mail","locationKey":"L9","title":"پیامک","attributeValueVms":[{"value":"600 پیامک | 6 ماهه (100 پیامک هر ماه)","displayText":"600 پیامک | 6 ماهه (100 پیامک هر ماه)"}],"shortcut":false},{"icon":null,"locationKey":null,"title":"الگوی شماره","attributeValueVms":[{"value":"NORMAL","displayText":"معمولی (سایر سیم‌کارت‌ها)"}],"shortcut":false},{"icon":"phone","locationKey":"L4","title":"مکالمه","attributeValueVms":[{"value":"٪۵۰ تخفیف ماهیانه مکالمه درون شبکه |به مدت 6 ماه","displayText":"٪۵۰ تخفیف ماهیانه مکالمه درون شبکه |به مدت 6 ماه"}],"shortcut":false},{"icon":null,"locationKey":null,"title":"offerId","attributeValueVms":[{"value":"144","displayText":"144"}],"shortcut":false},{"icon":"globe","locationKey":"L3","title":"اینترنت","attributeValueVms":[{"value":"30 گیگابایت | 1 ماهه ","displayText":"30 گیگابایت | 1 ماهه "}],"shortcut":false}],"createdOn":"2025-09-09T21:31:10.522"},{"id":690208,"name":"09112896256","productVariantId":686528,"slug":"09112896256","thumbnailUrl":null,"price":1668000.0,"priceWithTax":1732000,"discountPrice":1000000,"discountPercentage":40.0,"productStatus":"ACTIVE","productType":"EMERALD","attributes":[{"icon":null,"locationKey":null,"title":"Sku Code","attributeValueVms":[{"value":"MCCIMobNum","displayText":"MCCIMobNum"}],"shortcut":false},{"icon":null,"locationKey":"L1","title":"دائمی یا اعتباری","attributeValueVms":[{"value":"POSTPAID","displayText":"دائمی"}],"shortcut":false},{"icon":null,"locationKey":null,"title":"whId","attributeValueVms":[{"value":"10585201080747021","displayText":"10585201080747021"}],"shortcut":false},{"icon":null,"locationKey":null,"title":"Item Type Id","attributeValueVms":[{"value":"3004","displayText":"3004"}],"shortcut":false},{"icon":null,"locationKey":null,"title":"الگوی شماره","attributeValueVms":[{"value":"NORMAL","displayText":"معمولی (سایر سیم‌کارت‌ها)"}],"shortcut":false},{"icon":null,"locationKey":null,"title":"قیمت","attributeValueVms":[{"value":"1668000","displayText":"1668000"}],"shortcut":false},{"icon":"mail","locationKey":"L9","title":"پیامک","attributeValueVms":[{"value":"600 پیامک | 6 ماهه (100 پیامک هر ماه)","displayText":"600 پیامک | 6 ماهه (100 پیامک هر ماه)"}],"shortcut":false},{"icon":"phone","locationKey":"L4","title":"مکالمه","attributeValueVms":[{"value":"٪۵۰ تخفیف ماهیانه مکالمه درون شبکه |به مدت 6 ماه","displayText":"٪۵۰ تخفیف ماهیانه مکالمه درون شبکه |به مدت 6 ماه"}],"shortcut":false},{"icon":null,"locationKey":null,"title":"هدیه اینترنت","attributeValueVms":[{"value":"بین 5 تا 30 گیگابایت","displayText":"بین 5 تا 30 گیگابایت"}],"shortcut":false},{"icon":null,"locationKey":null,"title":"offerId","attributeValueVms":[{"value":"144","displayText":"144"}],"shortcut":false},{"icon":null,"locationKey":"L2","title":"نوع سیم‌کارت","attributeValueVms":[{"value":"EMERALD","displayText":"زمردی"}],"shortcut":false},{"icon":"globe","locationKey":"L3","title":"اینترنت","attributeValueVms":[{"value":"30 گیگابایت | 1 ماهه ","displayText":"30 گیگابایت | 1 ماهه "}],"shortcut":false}],"createdOn":"2025-09-09T21:31:11.944"},{"id":689564,"name":"09112893873","productVariantId":686449,"slug":"09112893873","thumbnailUrl":null,"price":1668000.0,"priceWithTax":1732000,"discountPrice":1000000,"discountPercentage":40.0,"productStatus":"ACTIVE","productType":"EMERALD","attributes":[{"icon":null,"locationKey":null,"title":"Sku Code","attributeValueVms":[{"value":"MCCIMobNum","displayText":"MCCIMobNum"}],"shortcut":false},{"icon":null,"locationKey":"L1","title":"دائمی یا اعتباری","attributeValueVms":[{"value":"POSTPAID","displayText":"دائمی"}],"shortcut":false},{"icon":null,"locationKey":null,"title":"whId","attributeValueVms":[{"value":"10585201080747021","displayText":"10585201080747021"}],"shortcut":false},{"icon":null,"locationKey":null,"title":"Item Type Id","attributeValueVms":[{"value":"3004","displayText":"3004"}],"shortcut":false},{"icon":null,"locationKey":null,"title":"الگوی شماره","attributeValueVms":[{"value":"NORMAL","displayText":"معمولی (سایر سیم‌کارت‌ها)"}],"shortcut":false},{"icon":null,"locationKey":null,"title":"هدیه اینترنت","attributeValueVms":[{"value":"بین 5 تا 30 گیگابایت","displayText":"بین 5 تا 30 گیگابایت"}],"shortcut":false},{"icon":null,"locationKey":null,"title":"قیمت","attributeValueVms":[{"value":"1668000","displayText":"1668000"}],"shortcut":false},{"icon":"mail","locationKey":"L9","title":"پیامک","attributeValueVms":[{"value":"600 پیامک | 6 ماهه (100 پیامک هر ماه)","displayText":"600 پیامک | 6 ماهه (100 پیامک هر ماه)"}],"shortcut":false},{"icon":null,"locationKey":"L2","title":"نوع سیم‌کارت","attributeValueVms":[{"value":"EMERALD","displayText":"زمردی"}],"shortcut":false},{"icon":"phone","locationKey":"L4","title":"مکالمه","attributeValueVms":[{"value":"٪۵۰ تخفیف ماهیانه مکالمه درون شبکه |به مدت 6 ماه","displayText":"٪۵۰ تخفیف ماهیانه مکالمه درون شبکه |به مدت 6 ماه"}],"shortcut":false},{"icon":null,"locationKey":null,"title":"offerId","attributeValueVms":[{"value":"144","displayText":"144"}],"shortcut":false},{"icon":"globe","locationKey":"L3","title":"اینترنت","attributeValueVms":[{"value":"30 گیگابایت | 1 ماهه ","displayText":"30 گیگابایت | 1 ماهه "}],"shortcut":false}],"createdOn":"2025-09-09T21:31:10.534"},{"id":690016,"name":"09112892571","productVariantId":686716,"slug":"09112892571","thumbnailUrl":null,"price":1668000.0,"priceWithTax":1732000,"discountPrice":1000000,"discountPercentage":40.0,"productStatus":"ACTIVE","productType":"EMERALD","attributes":[{"icon":null,"locationKey":null,"title":"Sku Code","attributeValueVms":[{"value":"MCCIMobNum","displayText":"MCCIMobNum"}],"shortcut":false},{"icon":null,"locationKey":"L1","title":"دائمی یا اعتباری","attributeValueVms":[{"value":"POSTPAID","displayText":"دائمی"}],"shortcut":false},{"icon":null,"locationKey":null,"title":"whId","attributeValueVms":[{"value":"10585201080747021","displayText":"10585201080747021"}],"shortcut":false},{"icon":null,"locationKey":null,"title":"Item Type Id","attributeValueVms":[{"value":"3004","displayText":"3004"}],"shortcut":false},{"icon":null,"locationKey":null,"title":"الگوی شماره","attributeValueVms":[{"value":"NORMAL","displayText":"معمولی (سایر سیم‌کارت‌ها)"}],"shortcut":false},{"icon":null,"locationKey":"L2","title":"نوع سیم‌کارت","attributeValueVms":[{"value":"EMERALD","displayText":"زمردی"}],"shortcut":false},{"icon":"mail","locationKey":"L9","title":"پیامک","attributeValueVms":[{"value":"600 پیامک | 6 ماهه (100 پیامک هر ماه)","displayText":"600 پیامک | 6 ماهه (100 پیامک هر ماه)"}],"shortcut":false},{"icon":null,"locationKey":null,"title":"هدیه اینترنت","attributeValueVms":[{"value":"بین 5 تا 30 گیگابایت","displayText":"بین 5 تا 30 گیگابایت"}],"shortcut":false},{"icon":"phone","locationKey":"L4","title":"مکالمه","attributeValueVms":[{"value":"٪۵۰ تخفیف ماهیانه مکالمه درون شبکه |به مدت 6 ماه","displayText":"٪۵۰ تخفیف ماهیانه مکالمه درون شبکه |به مدت 6 ماه"}],"shortcut":false},{"icon":null,"locationKey":null,"title":"قیمت","attributeValueVms":[{"value":"1668000","displayText":"1668000"}],"shortcut":false},{"icon":null,"locationKey":null,"title":"offerId","attributeValueVms":[{"value":"144","displayText":"144"}],"shortcut":false},{"icon":"globe","locationKey":"L3","title":"اینترنت","attributeValueVms":[{"value":"30 گیگابایت | 1 ماهه ","displayText":"30 گیگابایت | 1 ماهه "}],"shortcut":false}],"createdOn":"2025-09-09T21:31:11.523"},{"id":689612,"name":"09112648278","productVariantId":686059,"slug":"09112648278","thumbnailUrl":null,"price":1668000.0,"priceWithTax":1732000,"discountPrice":1000000,"discountPercentage":40.0,"productStatus":"ACTIVE","productType":"EMERALD","attributes":[{"icon":"globe","locationKey":"L3","title":"اینترنت","attributeValueVms":[{"value":"30 گیگابایت | 1 ماهه ","displayText":"30 گیگابایت | 1 ماهه "}],"shortcut":false},{"icon":"phone","locationKey":"L4","title":"مکالمه","attributeValueVms":[{"value":"٪۵۰ تخفیف ماهیانه مکالمه درون شبکه |به مدت 6 ماه","displayText":"٪۵۰ تخفیف ماهیانه مکالمه درون شبکه |به مدت 6 ماه"}],"shortcut":false},{"icon":null,"locationKey":null,"title":"هدیه اینترنت","attributeValueVms":[{"value":"بین 5 تا 30 گیگابایت","displayText":"بین 5 تا 30 گیگابایت"}],"shortcut":false},{"icon":null,"locationKey":null,"title":"Sku Code","attributeValueVms":[{"value":"MCCIMobNum","displayText":"MCCIMobNum"}],"shortcut":false},{"icon":null,"locationKey":null,"title":"whId","attributeValueVms":[{"value":"10585201080747021","displayText":"10585201080747021"}],"shortcut":false},{"icon":null,"locationKey":null,"title":"الگوی شماره","attributeValueVms":[{"value":"NORMAL","displayText":"معمولی (سایر سیم‌کارت‌ها)"}],"shortcut":false},{"icon":"mail","locationKey":"L9","title":"پیامک","attributeValueVms":[{"value":"600 پیامک | 6 ماهه (100 پیامک هر ماه)","displayText":"600 پیامک | 6 ماهه (100 پیامک هر ماه)"}],"shortcut":false},{"icon":null,"locationKey":"L2","title":"نوع سیم‌کارت","attributeValueVms":[{"value":"EMERALD","displayText":"زمردی"}],"shortcut":false},{"icon":null,"locationKey":null,"title":"Item Type Id","attributeValueVms":[{"value":"3004","displayText":"3004"}],"shortcut":false},{"icon":null,"locationKey":"L1","title":"دائمی یا اعتباری","attributeValueVms":[{"value":"POSTPAID","displayText":"دائمی"}],"shortcut":false},{"icon":null,"locationKey":null,"title":"قیمت","attributeValueVms":[{"value":"1668000","displayText":"1668000"}],"shortcut":false},{"icon":null,"locationKey":null,"title":"offerId","attributeValueVms":[{"value":"144","displayText":"144"}],"shortcut":false}],"createdOn":"2025-09-09T21:31:10.632"},{"id":690235,"name":"09112892195","productVariantId":688059,"slug":"09112892195","thumbnailUrl":null,"price":1668000.0,"priceWithTax":1732000,"discountPrice":1000000,"discountPercentage":40.0,"productStatus":"ACTIVE","productType":"EMERALD","attributes":[{"icon":"globe","locationKey":"L3","title":"اینترنت","attributeValueVms":[{"value":"30 گیگابایت | 1 ماهه ","displayText":"30 گیگابایت | 1 ماهه "}],"shortcut":false},{"icon":"phone","locationKey":"L4","title":"مکالمه","attributeValueVms":[{"value":"٪۵۰ تخفیف ماهیانه مکالمه درون شبکه |به مدت 6 ماه","displayText":"٪۵۰ تخفیف ماهیانه مکالمه درون شبکه |به مدت 6 ماه"}],"shortcut":false},{"icon":null,"locationKey":null,"title":"هدیه اینترنت","attributeValueVms":[{"value":"بین 5 تا 30 گیگابایت","displayText":"بین 5 تا 30 گیگابایت"}],"shortcut":false},{"icon":null,"locationKey":null,"title":"Sku Code","attributeValueVms":[{"value":"MCCIMobNum","displayText":"MCCIMobNum"}],"shortcut":false},{"icon":null,"locationKey":null,"title":"whId","attributeValueVms":[{"value":"10585201080747021","displayText":"10585201080747021"}],"shortcut":false},{"icon":null,"locationKey":null,"title":"الگوی شماره","attributeValueVms":[{"value":"NORMAL","displayText":"معمولی (سایر سیم‌کارت‌ها)"}],"shortcut":false},{"icon":"mail","locationKey":"L9","title":"پیامک","attributeValueVms":[{"value":"600 پیامک | 6 ماهه (100 پیامک هر ماه)","displayText":"600 پیامک | 6 ماهه (100 پیامک هر ماه)"}],"shortcut":false},{"icon":null,"locationKey":"L2","title":"نوع سیم‌کارت","attributeValueVms":[{"value":"EMERALD","displayText":"زمردی"}],"shortcut":false},{"icon":null,"locationKey":null,"title":"Item Type Id","attributeValueVms":[{"value":"3004","displayText":"3004"}],"shortcut":false},{"icon":null,"locationKey":"L1","title":"دائمی یا اعتباری","attributeValueVms":[{"value":"POSTPAID","displayText":"دائمی"}],"shortcut":false},{"icon":null,"locationKey":null,"title":"قیمت","attributeValueVms":[{"value":"1668000","displayText":"1668000"}],"shortcut":false},{"icon":null,"locationKey":null,"title":"offerId","attributeValueVms":[{"value":"144","displayText":"144"}],"shortcut":false}],"createdOn":"2025-09-09T21:31:12.287"},{"id":689378,"name":"09112894234","productVariantId":686431,"slug":"09112894234","thumbnailUrl":null,"price":1668000.0,"priceWithTax":1732000,"discountPrice":1000000,"discountPercentage":40.0,"productStatus":"ACTIVE","productType":"EMERALD","attributes":[{"icon":"globe","locationKey":"L3","title":"اینترنت","attributeValueVms":[{"value":"30 گیگابایت | 1 ماهه ","displayText":"30 گیگابایت | 1 ماهه "}],"shortcut":false},{"icon":"phone","locationKey":"L4","title":"مکالمه","attributeValueVms":[{"value":"٪۵۰ تخفیف ماهیانه مکالمه درون شبکه |به مدت 6 ماه","displayText":"٪۵۰ تخفیف ماهیانه مکالمه درون شبکه |به مدت 6 ماه"}],"shortcut":false},{"icon":null,"locationKey":null,"title":"هدیه اینترنت","attributeValueVms":[{"value":"بین 5 تا 30 گیگابایت","displayText":"بین 5 تا 30 گیگابایت"}],"shortcut":false},{"icon":null,"locationKey":null,"title":"Sku Code","attributeValueVms":[{"value":"MCCIMobNum","displayText":"MCCIMobNum"}],"shortcut":false},{"icon":null,"locationKey":null,"title":"whId","attributeValueVms":[{"value":"10585201080747021","displayText":"10585201080747021"}],"shortcut":false},{"icon":null,"locationKey":null,"title":"الگوی شماره","attributeValueVms":[{"value":"NORMAL","displayText":"معمولی (سایر سیم‌کارت‌ها)"}],"shortcut":false},{"icon":"mail","locationKey":"L9","title":"پیامک","attributeValueVms":[{"value":"600 پیامک | 6 ماهه (100 پیامک هر ماه)","displayText":"600 پیامک | 6 ماهه (100 پیامک هر ماه)"}],"shortcut":false},{"icon":null,"locationKey":"L2","title":"نوع سیم‌کارت","attributeValueVms":[{"value":"EMERALD","displayText":"زمردی"}],"shortcut":false},{"icon":null,"locationKey":null,"title":"Item Type Id","attributeValueVms":[{"value":"3004","displayText":"3004"}],"shortcut":false},{"icon":null,"locationKey":"L1","title":"دائمی یا اعتباری","attributeValueVms":[{"value":"POSTPAID","displayText":"دائمی"}],"shortcut":false},{"icon":null,"locationKey":null,"title":"قیمت","attributeValueVms":[{"value":"1668000","displayText":"1668000"}],"shortcut":false},{"icon":null,"locationKey":null,"title":"offerId","attributeValueVms":[{"value":"144","displayText":"144"}],"shortcut":false}],"createdOn":"2025-09-09T21:31:10.206"},{"id":688182,"name":"09112654286","productVariantId":685343,"slug":"09112654286","thumbnailUrl":null,"price":1668000.0,"priceWithTax":1732000,"discountPrice":1000000,"discountPercentage":40.0,"productStatus":"ACTIVE","productType":"EMERALD","attributes":[{"icon":"globe","locationKey":"L3","title":"اینترنت","attributeValueVms":[{"value":"30 گیگابایت | 1 ماهه ","displayText":"30 گیگابایت | 1 ماهه "}],"shortcut":false},{"icon":"phone","locationKey":"L4","title":"مکالمه","attributeValueVms":[{"value":"٪۵۰ تخفیف ماهیانه مکالمه درون شبکه |به مدت 6 ماه","displayText":"٪۵۰ تخفیف ماهیانه مکالمه درون شبکه |به مدت 6 ماه"}],"shortcut":false},{"icon":null,"locationKey":null,"title":"هدیه اینترنت","attributeValueVms":[{"value":"بین 5 تا 30 گیگابایت","displayText":"بین 5 تا 30 گیگابایت"}],"shortcut":false},{"icon":null,"locationKey":null,"title":"Sku Code","attributeValueVms":[{"value":"MCCIMobNum","displayText":"MCCIMobNum"}],"shortcut":false},{"icon":null,"locationKey":null,"title":"whId","attributeValueVms":[{"value":"10585201080747021","displayText":"10585201080747021"}],"shortcut":false},{"icon":null,"locationKey":null,"title":"الگوی شماره","attributeValueVms":[{"value":"NORMAL","displayText":"معمولی (سایر سیم‌کارت‌ها)"}],"shortcut":false},{"icon":"mail","locationKey":"L9","title":"پیامک","attributeValueVms":[{"value":"600 پیامک | 6 ماهه (100 پیامک هر ماه)","displayText":"600 پیامک | 6 ماهه (100 پیامک هر ماه)"}],"shortcut":false},{"icon":null,"locationKey":"L2","title":"نوع سیم‌کارت","attributeValueVms":[{"value":"EMERALD","displayText":"زمردی"}],"shortcut":false},{"icon":null,"locationKey":null,"title":"Item Type Id","attributeValueVms":[{"value":"3004","displayText":"3004"}],"shortcut":false},{"icon":null,"locationKey":"L1","title":"دائمی یا اعتباری","attributeValueVms":[{"value":"POSTPAID","displayText":"دائمی"}],"shortcut":false},{"icon":null,"locationKey":null,"title":"قیمت","attributeValueVms":[{"value":"1668000","displayText":"1668000"}],"shortcut":false},{"icon":null,"locationKey":null,"title":"offerId","attributeValueVms":[{"value":"144","displayText":"144"}],"shortcut":false}],"createdOn":"2025-09-09T21:31:07.561"}],"pageNo":126,"pageSize":16,"totalElements":2523,"totalPages":158,"isLast":false}
