{"products":[{"id":688139,"name":"09112632679","productVariantId":685270,"slug":"09112632679","thumbnailUrl":null,"price":1668000.0,"priceWithTax":null,"discountPrice":1000000,"discountPercentage":40.0,"productStatus":"ACTIVE","productType":"EMERALD","attributes":[{"icon":"globe","locationKey":"L3","title":"اینترنت","attributeValueVms":[{"value":"30 گیگابایت | 1 ماهه ","displayText":"30 گیگابایت | 1 ماهه "}],"shortcut":false},{"icon":"phone","locationKey":"L4","title":"مکالمه","attributeValueVms":[{"value":"٪۵۰ تخفیف ماهیانه مکالمه درون شبکه |به مدت 6 ماه","displayText":"٪۵۰ تخفیف ماهیانه مکالمه درون شبکه |به مدت 6 ماه"}],"shortcut":false},{"icon":null,"locationKey":null,"title":"هدیه اینترنت","attributeValueVms":[{"value":"بین 5 تا 30 گیگابایت","displayText":"بین 5 تا 30 گیگابایت"}],"shortcut":false},{"icon":null,"locationKey":null,"title":"Sku Code","attributeValueVms":[{"value":"MCCIMobNum","displayText":"MCCIMobNum"}],"shortcut":false},{"icon":null,"locationKey":null,"title":"whId","attributeValueVms":[{"value":"10585201080747021","displayText":"10585201080747021"}],"shortcut":false},{"icon":null,"locationKey":null,"title":"الگوی شماره","attributeValueVms":[{"value":"NORMAL","displayText":"معمولی (سایر سیم‌کارت‌ها)"}],"shortcut":false},{"icon":"mail","locationKey":"L9","title":"پیامک","attributeValueVms":[{"value":"600 پیامک | 6 ماهه (100 پیامک هر ماه)","displayText":"600 پیامک | 6 ماهه (100 پیامک هر ماه)"}],"shortcut":false},{"icon":null,"locationKey":"L2","title":"نوع سیم‌کارت","attributeValueVms":[{"value":"EMERALD","displayText":"زمردی"}],"shortcut":false},{"icon":null,"locationKey":null,"title":"Item Type Id","attributeValueVms":[{"value":"3004","displayText":"3004"}],"shortcut":false},{"icon":null,"locationKey":"L1","title":"دائمی یا اعتباری","attributeValueVms":[{"value":"POSTPAID","displayText":"دائمی"}],"shortcut":false},{"icon":null,"locationKey":null,"title":"قیمت","attributeValueVms":[{"value":"1668000","displayText":"1668000"}],"shortcut":false},{"icon":null,"locationKey":null,"title":"offerId","attributeValueVms":[{"value":"144","displayText":"144"}],"shortcut":false}],"createdOn":"2025-09-09T21:31:07.471"},{"id":687273,"name":"09112653814","productVariantId":684066,"slug":"09112653814","thumbnailUrl":null,"price":1668000.0,"priceWithTax":null,"discountPrice":1000000,"discountPercentage":40.0,"productStatus":"ACTIVE","productType":"EMERALD","attributes":[{"icon":"globe","locationKey":"L3","title":"اینترنت","attributeValueVms":[{"value":"30 گیگابایت | 1 ماهه ","displayText":"30 گیگابایت | 1 ماهه "}],"shortcut":false},{"icon":"phone","locationKey":"L4","title":"مکالمه","attributeValueVms":[{"value":"٪۵۰ تخفیف ماهیانه مکالمه درون شبکه |به مدت 6 ماه","displayText":"٪۵۰ تخفیف ماهیانه مکالمه درون شبکه |به مدت 6 ماه"}],"shortcut":false},{"icon":null,"locationKey":null,"title":"هدیه اینترنت","attributeValueVms":[{"value":"بین 5 تا 30 گیگابایت","displayText":"بین 5 تا 30 گیگابایت"}],"shortcut":false},{"icon":null,"locationKey":null,"title":"Sku Code","attributeValueVms":[{"value":"MCCIMobNum","displayText":"MCCIMobNum"}],"shortcut":false},{"icon":null,"locationKey":null,"title":"whId","attributeValueVms":[{"value":"10585201080747021","displayText":"10585201080747021"}],"shortcut":false},{"icon":null,"locationKey":null,"title":"الگوی شماره","attributeValueVms":[{"value":"NORMAL","displayText":"معمولی (سایر سیم‌کارت‌ها)"}],"shortcut":false},{"icon":"mail","locationKey":"L9","title":"پیامک","attributeValueVms":[{"value":"600 پیامک | 6 ماهه (100 پیامک هر ماه)","displayText":"600 پیامک | 6 ماهه (100 پیامک هر ماه)"}],"shortcut":false},{"icon":null,"locationKey":"L2","title":"نوع سیم‌کارت","attributeValueVms":[{"value":"EMERALD","displayText":"زمردی"}],"shortcut":false},{"icon":null,"locationKey":null,"title":"Item Type Id","attributeValueVms":[{"value":"3004","displayText":"3004"}],"shortcut":false},{"icon":null,"locationKey":"L1","title":"دائمی یا اعتباری","attributeValueVms":[{"value":"POSTPAID","displayText":"دائمی"}],"shortcut":false},{"icon":null,"locationKey":null,"title":"قیمت","attributeValueVms":[{"value":"1668000","displayText":"1668000"}],"shortcut":false},{"icon":null,"locationKey":null,"title":"offerId","attributeValueVms":[{"value":"144","displayText":"144"}],"shortcut":false}],"createdOn":"2025-09-09T21:31:03.708"},{"id":689718,"name":"09112631924","productVariantId":686402,"slug":"09112631924","thumbnailUrl":null,"price":1668000.0,"priceWithTax":null,"discountPrice":1000000,"discountPercentage":40.0,"productStatus":"ACTIVE","productType":"EMERALD","attributes":[{"icon":"globe","locationKey":"L3","title":"اینترنت","attributeValueVms":[{"value":"30 گیگابایت | 1 ماهه ","displayText":"30 گیگابایت | 1 ماهه "}],"shortcut":false},{"icon":"phone","locationKey":"L4","title":"مکالمه","attributeValueVms":[{"value":"٪۵۰ تخفیف ماهیانه مکالمه درون شبکه |به مدت 6 ماه","displayText":"٪۵۰ تخفیف ماهیانه مکالمه درون شبکه |به مدت 6 ماه"}],"shortcut":false},{"icon":null,"locationKey":null,"title":"هدیه اینترنت","attributeValueVms":[{"value":"بین 5 تا 30 گیگابایت","displayText":"بین 5 تا 30 گیگابایت"}],"shortcut":false},{"icon":null,"locationKey":null,"title":"Sku Code","attributeValueVms":[{"value":"MCCIMobNum","displayText":"MCCIMobNum"}],"shortcut":false},{"icon":null,"locationKey":null,"title":"whId","attributeValueVms":[{"value":"10585201080747021","displayText":"10585201080747021"}],"shortcut":false},{"icon":null,"locationKey":null,"title":"الگوی شماره","attributeValueVms":[{"value":"NORMAL","displayText":"معمولی (سایر سیم‌کارت‌ها)"}],"shortcut":false},{"icon":"mail","locationKey":"L9","title":"پیامک","attributeValueVms":[{"value":"600 پیامک | 6 ماهه (100 پیامک هر ماه)","displayText":"600 پیامک | 6 ماهه (100 پیامک هر ماه)"}],"shortcut":false},{"icon":null,"locationKey":"L2","title":"نوع سیم‌کارت","attributeValueVms":[{"value":"EMERALD","displayText":"زمردی"}],"shortcut":false},{"icon":null,"locationKey":null,"title":"Item Type Id","attributeValueVms":[{"value":"3004","displayText":"3004"}],"shortcut":false},{"icon":null,"locationKey":"L1","title":"دائمی یا اعتباری","attributeValueVms":[{"value":"POSTPAID","displayText":"دائمی"}],"shortcut":false},{"icon":null,"locationKey":null,"title":"قیمت","attributeValueVms":[{"value":"1668000","displayText":"1668000"}],"shortcut":false},{"icon":null,"locationKey":null,"title":"offerId","attributeValueVms":[{"value":"144","displayText":"144"}],"shortcut":false}],"createdOn":"2025-09-09T21:31:10.891"},{"id":689314,"name":"09112631824","productVariantId":686012,"slug":"09112631824","thumbnailUrl":null,"price":1668000.0,"priceWithTax":null,"discountPrice":1000000,"discountPercentage":40.0,"productStatus":"ACTIVE","productType":"EMERALD","attributes":[{"icon":"globe","locationKey":"L3","title":"اینترنت","attributeValueVms":[{"value":"30 گیگابایت | 1 ماهه ","displayText":"30 گیگابایت | 1 ماهه "}],"shortcut":false},{"icon":"phone","locationKey":"L4","title":"مکالمه","attributeValueVms":[{"value":"٪۵۰ تخفیف ماهیانه مکالمه درون شبکه |به مدت 6 ماه","displayText":"٪۵۰ تخفیف ماهیانه مکالمه درون شبکه |به مدت 6 ماه"}],"shortcut":false},{"icon":null,"locationKey":null,"title":"هدیه اینترنت","attributeValueVms":[{"value":"بین 5 تا 30 گیگابایت","displayText":"بین 5 تا 30 گیگابایت"}],"shortcut":false},{"icon":null,"locationKey":null,"title":"Sku Code","attributeValueVms":[{"value":"MCCIMobNum","displayText":"MCCIMobNum"}],"shortcut":false},{"icon":null,"locationKey":null,"title":"whId","attributeValueVms":[{"value":"10585201080747021","displayText":"10585201080747021"}],"shortcut":false},{"icon":null,"locationKey":null,"title":"الگوی شماره","attributeValueVms":[{"value":"NORMAL","displayText":"معمولی (سایر سیم‌کارت‌ها)"}],"shortcut":false},{"icon":"mail","locationKey":"L9","title":"پیامک","attributeValueVms":[{"value":"600 پیامک | 6 ماهه (100 پیامک هر ماه)","displayText":"600 پیامک | 6 ماهه (100 پیامک هر ماه)"}],"shortcut":false},{"icon":null,"locationKey":"L2","title":"نوع سیم‌کارت","attributeValueVms":[{"value":"EMERALD","displayText":"زمردی"}],"shortcut":false},{"icon":null,"locationKey":null,"title":"Item Type Id","attributeValueVms":[{"value":"3004","displayText":"3004"}],"shortcut":false},{"icon":null,"locationKey":"L1","title":"دائمی یا اعتباری","attributeValueVms":[{"value":"POSTPAID","displayText":"دائمی"}],"shortcut":false},{"icon":null,"locationKey":null,"title":"قیمت","attributeValueVms":[{"value":"1668000","displayText":"1668000"}],"shortcut":false},{"icon":null,"locationKey":null,"title":"offerId","attributeValueVms":[{"value":"144","displayText":"144"}],"shortcut":false}],"createdOn":"2025-09-09T21:31:10.087"},{"id":685000,"name":"09112612937","productVariantId":681887,"slug":"09112612937","thumbnailUrl":null,"price":1668000.0,"priceWithTax":null,"discountPrice":1000000,"discountPercentage":40.0,"productStatus":"ACTIVE","productType":"EMERALD","attributes":[{"icon":"globe","locationKey":"L3","title":"اینترنت","attributeValueVms":[{"value":"30 گیگابایت | 1 ماهه ","displayText":"30 گیگابایت | 1 ماهه "}],"shortcut":false},{"icon":"phone","locationKey":"L4","title":"مکالمه","attributeValueVms":[{"value":"٪۵۰ تخفیف ماهیانه مکالمه درون شبکه |به مدت 6 ماه","displayText":"٪۵۰ تخفیف ماهیانه مکالمه درون شبکه |به مدت 6 ماه"}],"shortcut":false},{"icon":null,"locationKey":null,"title":"هدیه اینترنت","attributeValueVms":[{"value":"بین 5 تا 30 گیگابایت","displayText":"بین 5 تا 30 گیگابایت"}],"shortcut":false},{"icon":null,"locationKey":null,"title":"Sku Code","attributeValueVms":[{"value":"MCCIMobNum","displayText":"MCCIMobNum"}],"shortcut":false},{"icon":null,"locationKey":null,"title":"whId","attributeValueVms":[{"value":"10585201080747021","displayText":"10585201080747021"}],"shortcut":false},{"icon":null,"locationKey":null,"title":"الگوی شماره","attributeValueVms":[{"value":"NORMAL","displayText":"معمولی (سایر سیم‌کارت‌ها)"}],"shortcut":false},{"icon":"mail","locationKey":"L9","title":"پیامک","attributeValueVms":[{"value":"600 پیامک | 6 ماهه (100 پیامک هر ماه)","displayText":"600 پیامک | 6 ماهه (100 پیامک هر ماه)"}],"shortcut":false},{"icon":null,"locationKey":"L2","title":"نوع سیم‌کارت","attributeValueVms":[{"value":"EMERALD","displayText":"زمردی"}],"shortcut":false},{"icon":null,"locationKey":null,"title":"Item Type Id","attributeValueVms":[{"value":"3004","displayText":"3004"}],"shortcut":false},{"icon":null,"locationKey":"L1","title":"دائمی یا اعتباری","attributeValueVms":[{"value":"POSTPAID","displayText":"دائمی"}],"shortcut":false},{"icon":null,"locationKey":null,"title":"قیمت","attributeValueVms":[{"value":"1668000","displayText":"1668000"}],"shortcut":false},{"icon":null,"locationKey":null,"title":"offerId","attributeValueVms":[{"value":"144","displayText":"144"}],"shortcut":false}],"createdOn":"2025-09-09T21:30:56.843"},{"id":688144,"name":"09112632519","productVariantId":685243,"slug":"09112632519","thumbnailUrl":null,"price":1668000.0,"priceWithTax":null,"discountPrice":1000000,"discountPercentage":40.0,"productStatus":"ACTIVE","productType":"EMERALD","attributes":[{"icon":"globe","locationKey":"L3","title":"اینترنت","attributeValueVms":[{"value":"30 گیگابایت | 1 ماهه ","displayText":"30 گیگابایت | 1 ماهه "}],"shortcut":false},{"icon":"phone","locationKey":"L4","title":"مکالمه","attributeValueVms":[{"value":"٪۵۰ تخفیف ماهیانه مکالمه درون شبکه |به مدت 6 ماه","displayText":"٪۵۰ تخفیف ماهیانه مکالمه درون شبکه |به مدت 6 ماه"}],"shortcut":false},{"icon":null,"locationKey":null,"title":"هدیه اینترنت","attributeValueVms":[{"value":"بین 5 تا 30 گیگابایت","displayText":"بین 5 تا 30 گیگابایت"}],"shortcut":false},{"icon":null,"locationKey":null,"title":"Sku Code","attributeValueVms":[{"value":"MCCIMobNum","displayText":"MCCIMobNum"}],"shortcut":false},{"icon":null,"locationKey":null,"title":"whId","attributeValueVms":[{"value":"10585201080747021","displayText":"10585201080747021"}],"shortcut":false},{"icon":null,"locationKey":null,"title":"الگوی شماره","attributeValueVms":[{"value":"NORMAL","displayText":"معمولی (سایر سیم‌کارت‌ها)"}],"shortcut":false},{"icon":"mail","locationKey":"L9","title":"پیامک","attributeValueVms":[{"value":"600 پیامک | 6 ماهه (100 پیامک هر ماه)","displayText":"600 پیامک | 6 ماهه (100 پیامک هر ماه)"}],"shortcut":false},{"icon":null,"locationKey":"L2","title":"نوع سیم‌کارت","attributeValueVms":[{"value":"EMERALD","displayText":"زمردی"}],"shortcut":false},{"icon":null,"locationKey":null,"title":"Item Type Id","attributeValueVms":[{"value":"3004","displayText":"3004"}],"shortcut":false},{"icon":null,"locationKey":"L1","title":"دائمی یا اعتباری","attributeValueVms":[{"value":"POSTPAID","displayText":"دائمی"}],"shortcut":false},{"icon":null,"locationKey":null,"title":"قیمت","attributeValueVms":[{"value":"1668000","displayText":"1668000"}],"shortcut":false},{"icon":null,"locationKey":null,"title":"offerId","attributeValueVms":[{"value":"144","displayText":"144"}],"shortcut":false}],"createdOn":"2025-09-09T21:31:07.486"},{"id":688385,"name":"09112631896","productVariantId":685440,"slug":"09112631896","thumbnailUrl":null,"price":1668000.0,"priceWithTax":null,"discountPrice":1000000,"discountPercentage":40.0,"productStatus":"ACTIVE","productType":"EMERALD","attributes":[{"icon":"globe","locationKey":"L3","title":"اینترنت","attributeValueVms":[{"value":"30 گیگابایت | 1 ماهه ","displayText":"30 گیگابایت | 1 ماهه "}],"shortcut":false},{"icon":"phone","locationKey":"L4","title":"مکالمه","attributeValueVms":[{"value":"٪۵۰ تخفیف ماهیانه مکالمه درون شبکه |به مدت 6 ماه","displayText":"٪۵۰ تخفیف ماهیانه مکالمه درون شبکه |به مدت 6 ماه"}],"shortcut":false},{"icon":null,"locationKey":null,"title":"هدیه اینترنت","attributeValueVms":[{"value":"بین 5 تا 30 گیگابایت","displayText":"بین 5 تا 30 گیگابایت"}],"shortcut":false},{"icon":null,"locationKey":null,"title":"Sku Code","attributeValueVms":[{"value":"MCCIMobNum","displayText":"MCCIMobNum"}],"shortcut":false},{"icon":null,"locationKey":null,"title":"whId","attributeValueVms":[{"value":"10585201080747021","displayText":"10585201080747021"}],"shortcut":false},{"icon":null,"locationKey":null,"title":"الگوی شماره","attributeValueVms":[{"value":"NORMAL","displayText":"معمولی (سایر سیم‌کارت‌ها)"}],"shortcut":false},{"icon":"mail","locationKey":"L9","title":"پیامک","attributeValueVms":[{"value":"600 پیامک | 6 ماهه (100 پیامک هر ماه)","displayText":"600 پیامک | 6 ماهه (100 پیامک هر ماه)"}],"shortcut":false},{"icon":null,"locationKey":"L2","title":"نوع سیم‌کارت","attributeValueVms":[{"value":"EMERALD","displayText":"زمردی"}],"shortcut":false},{"icon":null,"locationKey":null,"title":"Item Type Id","attributeValueVms":[{"value":"3004","displayText":"3004"}],"shortcut":false},{"icon":null,"locationKey":"L1","title":"دائمی یا اعتباری","attributeValueVms":[{"value":"POSTPAID","displayText":"دائمی"}],"shortcut":false},{"icon":null,"locationKey":null,"title":"قیمت","attributeValueVms":[{"value":"1668000","displayText":"1668000"}],"shortcut":false},{"icon":null,"locationKey":null,"title":"offerId","attributeValueVms":[{"value":"144","displayText":"144"}],"shortcut":false}],"createdOn":"2025-09-09T21:31:08.013"},{"id":688824,"name":"09112679213","productVariantId":685605,"slug":"09112679213","thumbnailUrl":null,"price":1668000.0,"priceWithTax":null,"discountPrice":1000000,"discountPercentage":40.0,"productStatus":"ACTIVE","productType":"EMERALD","attributes":[{"icon":"globe","locationKey":"L3","title":"اینترنت","attributeValueVms":[{"value":"30 گیگابایت | 1 ماهه ","displayText":"30 گیگابایت | 1 ماهه "}],"shortcut":false},{"icon":"phone","locationKey":"L4","title":"مکالمه","attributeValueVms":[{"value":"٪۵۰ تخفیف ماهیانه مکالمه درون شبکه |به مدت 6 ماه","displayText":"٪۵۰ تخفیف ماهیانه مکالمه درون شبکه |به مدت 6 ماه"}],"shortcut":false},{"icon":null,"locationKey":null,"title":"هدیه اینترنت","attributeValueVms":[{"value":"بین 5 تا 30 گیگابایت","displayText":"بین 5 تا 30 گیگابایت"}],"shortcut":false},{"icon":null,"locationKey":null,"title":"Sku Code","attributeValueVms":[{"value":"MCCIMobNum","displayText":"MCCIMobNum"}],"shortcut":false},{"icon":null,"locationKey":null,"title":"whId","attributeValueVms":[{"value":"10585201080747021","displayText":"10585201080747021"}],"shortcut":false},{"icon":null,"locationKey":null,"title":"الگوی شماره","attributeValueVms":[{"value":"NORMAL","displayText":"معمولی (سایر سیم‌کارت‌ها)"}],"shortcut":false},{"icon":"mail","locationKey":"L9","title":"پیامک","attributeValueVms":[{"value":"600 پیامک | 6 ماهه (100 پیامک هر ماه)","displayText":"600 پیامک | 6 ماهه (100 پیامک هر ماه)"}],"shortcut":false},{"icon":null,"locationKey":"L2","title":"نوع سیم‌کارت","attributeValueVms":[{"value":"EMERALD","displayText":"زمردی"}],"shortcut":false},{"icon":null,"locationKey":null,"title":"Item Type Id","attributeValueVms":[{"value":"3004","displayText":"3004"}],"shortcut":false},{"icon":null,"locationKey":"L1","title":"دائمی یا اعتباری","attributeValueVms":[{"value":"POSTPAID","displayText":"دائمی"}],"shortcut":false},{"icon":null,"locationKey":null,"title":"قیمت","attributeValueVms":[{"value":"1668000","displayText":"1668000"}],"shortcut":false},{"icon":null,"locationKey":null,"title":"offerId","attributeValueVms":[{"value":"144","displayText":"144"}],"shortcut":false}],"createdOn":"2025-09-09T21:31:08.923"},{"id":685267,"name":"09112674271","productVariantId":682314,"slug":"09112674271","thumbnailUrl":null,"price":1668000.0,"priceWithTax":null,"discountPrice":1000000,"discountPercentage":40.0,"productStatus":"ACTIVE","productType":"EMERALD","attributes":[{"icon":"globe","locationKey":"L3","title":"اینترنت","attributeValueVms":[{"value":"30 گیگابایت | 1 ماهه ","displayText":"30 گیگابایت | 1 ماهه "}],"shortcut":false},{"icon":"phone","locationKey":"L4","title":"مکالمه","attributeValueVms":[{"value":"٪۵۰ تخفیف ماهیانه مکالمه درون شبکه |به مدت 6 ماه","displayText":"٪۵۰ تخفیف ماهیانه مکالمه درون شبکه |به مدت 6 ماه"}],"shortcut":false},{"icon":null,"locationKey":null,"title":"هدیه اینترنت","attributeValueVms":[{"value":"بین 5 تا 30 گیگابایت","displayText":"بین 5 تا 30 گیگابایت"}],"shortcut":false},{"icon":null,"locationKey":null,"title":"Sku Code","attributeValueVms":[{"value":"MCCIMobNum","displayText":"MCCIMobNum"}],"shortcut":false},{"icon":null,"locationKey":null,"title":"whId","attributeValueVms":[{"value":"10585201080747021","displayText":"10585201080747021"}],"shortcut":false},{"icon":null,"locationKey":null,"title":"الگوی شماره","attributeValueVms":[{"value":"NORMAL","displayText":"معمولی (سایر سیم‌کارت‌ها)"}],"shortcut":false},{"icon":"mail","locationKey":"L9","title":"پیامک","attributeValueVms":[{"value":"600 پیامک | 6 ماهه (100 پیامک هر ماه)","displayText":"600 پیامک | 6 ماهه (100 پیامک هر ماه)"}],"shortcut":false},{"icon":null,"locationKey":"L2","title":"نوع سیم‌کارت","attributeValueVms":[{"value":"EMERALD","displayText":"زمردی"}],"shortcut":false},{"icon":null,"locationKey":null,"title":"Item Type Id","attributeValueVms":[{"value":"3004","displayText":"3004"}],"shortcut":false},{"icon":null,"locationKey":"L1","title":"دائمی یا اعتباری","attributeValueVms":[{"value":"POSTPAID","displayText":"دائمی"}],"shortcut":false},{"icon":null,"locationKey":null,"title":"قیمت","attributeValueVms":[{"value":"1668000","displayText":"1668000"}],"shortcut":false},{"icon":null,"locationKey":null,"title":"offerId","attributeValueVms":[{"value":"144","displayText":"144"}],"shortcut":false}],"createdOn":"2025-09-09T21:30:57.929"},{"id":684521,"name":"09112659817","productVariantId":680720,"slug":"09112659817","thumbnailUrl":null,"price":1668000.0,"priceWithTax":null,"discountPrice":1000000,"discountPercentage":40.0,"productStatus":"ACTIVE","productType":"EMERALD","attributes":[{"icon":"globe","locationKey":"L3","title":"اینترنت","attributeValueVms":[{"value":"30 گیگابایت | 1 ماهه ","displayText":"30 گیگابایت | 1 ماهه "}],"shortcut":false},{"icon":"phone","locationKey":"L4","title":"مکالمه","attributeValueVms":[{"value":"٪۵۰ تخفیف ماهیانه مکالمه درون شبکه |به مدت 6 ماه","displayText":"٪۵۰ تخفیف ماهیانه مکالمه درون شبکه |به مدت 6 ماه"}],"shortcut":false},{"icon":null,"locationKey":null,"title":"هدیه اینترنت","attributeValueVms":[{"value":"بین 5 تا 30 گیگابایت","displayText":"بین 5 تا 30 گیگابایت"}],"shortcut":false},{"icon":null,"locationKey":null,"title":"Sku Code","attributeValueVms":[{"value":"MCCIMobNum","displayText":"MCCIMobNum"}],"shortcut":false},{"icon":null,"locationKey":null,"title":"whId","attributeValueVms":[{"value":"10585201080747021","displayText":"10585201080747021"}],"shortcut":false},{"icon":null,"locationKey":null,"title":"الگوی شماره","attributeValueVms":[{"value":"NORMAL","displayText":"معمولی (سایر سیم‌کارت‌ها)"}],"shortcut":false},{"icon":"mail","locationKey":"L9","title":"پیامک","attributeValueVms":[{"value":"600 پیامک | 6 ماهه (100 پیامک هر ماه)","displayText":"600 پیامک | 6 ماهه (100 پیامک هر ماه)"}],"shortcut":false},{"icon":null,"locationKey":"L2","title":"نوع سیم‌کارت","attributeValueVms":[{"value":"EMERALD","displayText":"زمردی"}],"shortcut":false},{"icon":null,"locationKey":null,"title":"Item Type Id","attributeValueVms":[{"value":"3004","displayText":"3004"}],"shortcut":false},{"icon":null,"locationKey":"L1","title":"دائمی یا اعتباری","attributeValueVms":[{"value":"POSTPAID","displayText":"دائمی"}],"shortcut":false},{"icon":null,"locationKey":null,"title":"قیمت","attributeValueVms":[{"value":"1668000","displayText":"1668000"}],"shortcut":false},{"icon":null,"locationKey":null,"title":"offerId","attributeValueVms":[{"value":"144","displayText":"144"}],"shortcut":false}],"createdOn":"2025-09-09T21:30:55.029"},{"id":687669,"name":"09112651439","productVariantId":684485,"slug":"09112651439","thumbnailUrl":null,"price":1668000.0,"priceWithTax":null,"discountPrice":1000000,"discountPercentage":40.0,"productStatus":"ACTIVE","productType":"EMERALD","attributes":[{"icon":"globe","locationKey":"L3","title":"اینترنت","attributeValueVms":[{"value":"30 گیگابایت | 1 ماهه ","displayText":"30 گیگابایت | 1 ماهه "}],"shortcut":false},{"icon":"phone","locationKey":"L4","title":"مکالمه","attributeValueVms":[{"value":"٪۵۰ تخفیف ماهیانه مکالمه درون شبکه |به مدت 6 ماه","displayText":"٪۵۰ تخفیف ماهیانه مکالمه درون شبکه |به مدت 6 ماه"}],"shortcut":false},{"icon":null,"locationKey":null,"title":"هدیه اینترنت","attributeValueVms":[{"value":"بین 5 تا 30 گیگابایت","displayText":"بین 5 تا 30 گیگابایت"}],"shortcut":false},{"icon":null,"locationKey":null,"title":"Sku Code","attributeValueVms":[{"value":"MCCIMobNum","displayText":"MCCIMobNum"}],"shortcut":false},{"icon":null,"locationKey":null,"title":"whId","attributeValueVms":[{"value":"10585201080747021","displayText":"10585201080747021"}],"shortcut":false},{"icon":null,"locationKey":null,"title":"الگوی شماره","attributeValueVms":[{"value":"NORMAL","displayText":"معمولی (سایر سیم‌کارت‌ها)"}],"shortcut":false},{"icon":"mail","locationKey":"L9","title":"پیامک","attributeValueVms":[{"value":"600 پیامک | 6 ماهه (100 پیامک هر ماه)","displayText":"600 پیامک | 6 ماهه (100 پیامک هر ماه)"}],"shortcut":false},{"icon":null,"locationKey":"L2","title":"نوع سیم‌کارت","attributeValueVms":[{"value":"EMERALD","displayText":"زمردی"}],"shortcut":false},{"icon":null,"locationKey":null,"title":"Item Type Id","attributeValueVms":[{"value":"3004","displayText":"3004"}],"shortcut":false},{"icon":null,"locationKey":"L1","title":"دائمی یا اعتباری","attributeValueVms":[{"value":"POSTPAID","displayText":"دائمی"}],"shortcut":false},{"icon":null,"locationKey":null,"title":"قیمت","attributeValueVms":[{"value":"1668000","displayText":"1668000"}],"shortcut":false},{"icon":null,"locationKey":null,"title":"offerId","attributeValueVms":[{"value":"144","displayText":"144"}],"shortcut":false}],"createdOn":"2025-09-09T21:31:05.425"},{"id":686561,"name":"09112659432","productVariantId":683925,"slug":"09112659432","thumbnailUrl":null,"price":1668000.0,"priceWithTax":null,"discountPrice":1000000,"discountPercentage":40.0,"productStatus":"ACTIVE","productType":"EMERALD","attributes":[{"icon":"globe","locationKey":"L3","title":"اینترنت","attributeValueVms":[{"value":"30 گیگابایت | 1 ماهه ","displayText":"30 گیگابایت | 1 ماهه "}],"shortcut":false},{"icon":"phone","locationKey":"L4","title":"مکالمه","attributeValueVms":[{"value":"٪۵۰ تخفیف ماهیانه مکالمه درون شبکه |به مدت 6 ماه","displayText":"٪۵۰ تخفیف ماهیانه مکالمه درون شبکه |به مدت 6 ماه"}],"shortcut":false},{"icon":null,"locationKey":null,"title":"هدیه اینترنت","attributeValueVms":[{"value":"بین 5 تا 30 گیگابایت","displayText":"بین 5 تا 30 گیگابایت"}],"shortcut":false},{"icon":null,"locationKey":null,"title":"Sku Code","attributeValueVms":[{"value":"MCCIMobNum","displayText":"MCCIMobNum"}],"shortcut":false},{"icon":null,"locationKey":null,"title":"whId","attributeValueVms":[{"value":"10585201080747021","displayText":"10585201080747021"}],"shortcut":false},{"icon":null,"locationKey":null,"title":"الگوی شماره","attributeValueVms":[{"value":"NORMAL","displayText":"معمولی (سایر سیم‌کارت‌ها)"}],"shortcut":false},{"icon":"mail","locationKey":"L9","title":"پیامک","attributeValueVms":[{"value":"600 پیامک | 6 ماهه (100 پیامک هر ماه)","displayText":"600 پیامک | 6 ماهه (100 پیامک هر ماه)"}],"shortcut":false},{"icon":null,"locationKey":"L2","title":"نوع سیم‌کارت","attributeValueVms":[{"value":"EMERALD","displayText":"زمردی"}],"shortcut":false},{"icon":null,"locationKey":null,"title":"Item Type Id","attributeValueVms":[{"value":"3004","displayText":"3004"}],"shortcut":false},{"icon":null,"locationKey":"L1","title":"دائمی یا اعتباری","attributeValueVms":[{"value":"POSTPAID","displayText":"دائمی"}],"shortcut":false},{"icon":null,"locationKey":null,"title":"قیمت","attributeValueVms":[{"value":"1668000","displayText":"1668000"}],"shortcut":false},{"icon":null,"locationKey":null,"title":"offerId","attributeValueVms":[{"value":"144","displayText":"144"}],"shortcut":false}],"createdOn":"2025-09-09T21:31:01.88"},{"id":687917,"name":"09112672314","productVariantId":684381,"slug":"09112672314","thumbnailUrl":null,"price":1668000.0,"priceWithTax":null,"discountPrice":1000000,"discountPercentage":40.0,"productStatus":"ACTIVE","productType":"EMERALD","attributes":[{"icon":"globe","locationKey":"L3","title":"اینترنت","attributeValueVms":[{"value":"30 گیگابایت | 1 ماهه ","displayText":"30 گیگابایت | 1 ماهه "}],"shortcut":false},{"icon":"phone","locationKey":"L4","title":"مکالمه","attributeValueVms":[{"value":"٪۵۰ تخفیف ماهیانه مکالمه درون شبکه |به مدت 6 ماه","displayText":"٪۵۰ تخفیف ماهیانه مکالمه درون شبکه |به مدت 6 ماه"}],"shortcut":false},{"icon":null,"locationKey":null,"title":"هدیه اینترنت","attributeValueVms":[{"value":"بین 5 تا 30 گیگابایت","displayText":"بین 5 تا 30 گیگابایت"}],"shortcut":false},{"icon":null,"locationKey":null,"title":"Sku Code","attributeValueVms":[{"value":"MCCIMobNum","displayText":"MCCIMobNum"}],"shortcut":false},{"icon":null,"locationKey":null,"title":"whId","attributeValueVms":[{"value":"10585201080747021","displayText":"10585201080747021"}],"shortcut":false},{"icon":null,"locationKey":null,"title":"الگوی شماره","attributeValueVms":[{"value":"NORMAL","displayText":"معمولی (سایر سیم‌کارت‌ها)"}],"shortcut":false},{"icon":"mail","locationKey":"L9","title":"پیامک","attributeValueVms":[{"value":"600 پیامک | 6 ماهه (100 پیامک هر ماه)","displayText":"600 پیامک | 6 ماهه (100 پیامک هر ماه)"}],"shortcut":false},{"icon":null,"locationKey":"L2","title":"نوع سیم‌کارت","attributeValueVms":[{"value":"EMERALD","displayText":"زمردی"}],"shortcut":false},{"icon":null,"locationKey":null,"title":"Item Type Id","attributeValueVms":[{"value":"3004","displayText":"3004"}],"shortcut":false},{"icon":null,"locationKey":"L1","title":"دائمی یا اعتباری","attributeValueVms":[{"value":"POSTPAID","displayText":"دائمی"}],"shortcut":false},{"icon":null,"locationKey":null,"title":"قیمت","attributeValueVms":[{"value":"1668000","displayText":"1668000"}],"shortcut":false},{"icon":null,"locationKey":null,"title":"offerId","attributeValueVms":[{"value":"144","displayText":"144"}],"shortcut":false}],"createdOn":"2025-09-09T21:31:06.603"},{"id":687132,"name":"09112649789","productVariantId":684059,"slug":"09112649789","thumbnailUrl":null,"price":1668000.0,"priceWithTax":null,"discountPrice":1000000,"discountPercentage":40.0,"productStatus":"ACTIVE","productType":"EMERALD","attributes":[{"icon":"globe","locationKey":"L3","title":"اینترنت","attributeValueVms":[{"value":"30 گیگابایت | 1 ماهه ","displayText":"30 گیگابایت | 1 ماهه "}],"shortcut":false},{"icon":"phone","locationKey":"L4","title":"مکالمه","attributeValueVms":[{"value":"٪۵۰ تخفیف ماهیانه مکالمه درون شبکه |به مدت 6 ماه","displayText":"٪۵۰ تخفیف ماهیانه مکالمه درون شبکه |به مدت 6 ماه"}],"shortcut":false},{"icon":null,"locationKey":null,"title":"هدیه اینترنت","attributeValueVms":[{"value":"بین 5 تا 30 گیگابایت","displayText":"بین 5 تا 30 گیگابایت"}],"shortcut":false},{"icon":null,"locationKey":null,"title":"Sku Code","attributeValueVms":[{"value":"MCCIMobNum","displayText":"MCCIMobNum"}],"shortcut":false},{"icon":null,"locationKey":null,"title":"whId","attributeValueVms":[{"value":"10585201080747021","displayText":"10585201080747021"}],"shortcut":false},{"icon":null,"locationKey":null,"title":"الگوی شماره","attributeValueVms":[{"value":"NORMAL","displayText":"معمولی (سایر سیم‌کارت‌ها)"}],"shortcut":false},{"icon":"mail","locationKey":"L9","title":"پیامک","attributeValueVms":[{"value":"600 پیامک | 6 ماهه (100 پیامک هر ماه)","displayText":"600 پیامک | 6 ماهه (100 پیامک هر ماه)"}],"shortcut":false},{"icon":null,"locationKey":"L2","title":"نوع سیم‌کارت","attributeValueVms":[{"value":"EMERALD","displayText":"زمردی"}],"shortcut":false},{"icon":null,"locationKey":null,"title":"Item Type Id","attributeValueVms":[{"value":"3004","displayText":"3004"}],"shortcut":false},{"icon":null,"locationKey":"L1","title":"دائمی یا اعتباری","attributeValueVms":[{"value":"POSTPAID","displayText":"دائمی"}],"shortcut":false},{"icon":null,"locationKey":null,"title":"قیمت","attributeValueVms":[{"value":"1668000","displayText":"1668000"}],"shortcut":false},{"icon":null,"locationKey":null,"title":"offerId","attributeValueVms":[{"value":"144","displayText":"144"}],"shortcut":false}],"createdOn":"2025-09-09T21:31:03.394"},{"id":687405,"name":"09112632839","productVariantId":683634,"slug":"09112632839","thumbnailUrl":null,"price":1668000.0,"priceWithTax":null,"discountPrice":1000000,"discountPercentage":40.0,"productStatus":"ACTIVE","productType":"EMERALD","attributes":[{"icon":"globe","locationKey":"L3","title":"اینترنت","attributeValueVms":[{"value":"30 گیگابایت | 1 ماهه ","displayText":"30 گیگابایت | 1 ماهه "}],"shortcut":false},{"icon":"phone","locationKey":"L4","title":"مکالمه","attributeValueVms":[{"value":"٪۵۰ تخفیف ماهیانه مکالمه درون شبکه |به مدت 6 ماه","displayText":"٪۵۰ تخفیف ماهیانه مکالمه درون شبکه |به مدت 6 ماه"}],"shortcut":false},{"icon":null,"locationKey":null,"title":"هدیه اینترنت","attributeValueVms":[{"value":"بین 5 تا 30 گیگابایت","displayText":"بین 5 تا 30 گیگابایت"}],"shortcut":false},{"icon":null,"locationKey":null,"title":"Sku Code","attributeValueVms":[{"value":"MCCIMobNum","displayText":"MCCIMobNum"}],"shortcut":false},{"icon":null,"locationKey":null,"title":"whId","attributeValueVms":[{"value":"10585201080747021","displayText":"10585201080747021"}],"shortcut":false},{"icon":null,"locationKey":null,"title":"الگوی شماره","attributeValueVms":[{"value":"NORMAL","displayText":"معمولی (سایر سیم‌کارت‌ها)"}],"shortcut":false},{"icon":"mail","locationKey":"L9","title":"پیامک","attributeValueVms":[{"value":"600 پیامک | 6 ماهه (100 پیامک هر ماه)","displayText":"600 پیامک | 6 ماهه (100 پیامک هر ماه)"}],"shortcut":false},{"icon":null,"locationKey":"L2","title":"نوع سیم‌کارت","attributeValueVms":[{"value":"EMERALD","displayText":"زمردی"}],"shortcut":false},{"icon":null,"locationKey":null,"title":"Item Type Id","attributeValueVms":[{"value":"3004","displayText":"3004"}],"shortcut":false},{"icon":null,"locationKey":"L1","title":"دائمی یا اعتباری","attributeValueVms":[{"value":"POSTPAID","displayText":"دائمی"}],"shortcut":false},{"icon":null,"locationKey":null,"title":"قیمت","attributeValueVms":[{"value":"1668000","displayText":"1668000"}],"shortcut":false},{"icon":null,"locationKey":null,"title":"offerId","attributeValueVms":[{"value":"144","displayText":"144"}],"shortcut":false}],"createdOn":"2025-09-09T21:31:04.103"},{"id":687510,"name":"09112614738","productVariantId":683738,"slug":"09112614738","thumbnailUrl":null,"price":1668000.0,"priceWithTax":null,"discountPrice":1000000,"discountPercentage":40.0,"productStatus":"ACTIVE","productType":"EMERALD","attributes":[{"icon":"globe","locationKey":"L3","title":"اینترنت","attributeValueVms":[{"value":"30 گیگابایت | 1 ماهه ","displayText":"30 گیگابایت | 1 ماهه "}],"shortcut":false},{"icon":"phone","locationKey":"L4","title":"مکالمه","attributeValueVms":[{"value":"٪۵۰ تخفیف ماهیانه مکالمه درون شبکه |به مدت 6 ماه","displayText":"٪۵۰ تخفیف ماهیانه مکالمه درون شبکه |به مدت 6 ماه"}],"shortcut":false},{"icon":null,"locationKey":null,"title":"هدیه اینترنت","attributeValueVms":[{"value":"بین 5 تا 30 گیگابایت","displayText":"بین 5 تا 30 گیگابایت"}],"shortcut":false},{"icon":null,"locationKey":null,"title":"Sku Code","attributeValueVms":[{"value":"MCCIMobNum","displayText":"MCCIMobNum"}],"shortcut":false},{"icon":null,"locationKey":null,"title":"whId","attributeValueVms":[{"value":"10585201080747021","displayText":"10585201080747021"}],"shortcut":false},{"icon":null,"locationKey":null,"title":"الگوی شماره","attributeValueVms":[{"value":"NORMAL","displayText":"معمولی (سایر سیم‌کارت‌ها)"}],"shortcut":false},{"icon":"mail","locationKey":"L9","title":"پیامک","attributeValueVms":[{"value":"600 پیامک | 6 ماهه (100 پیامک هر ماه)","displayText":"600 پیامک | 6 ماهه (100 پیامک هر ماه)"}],"shortcut":false},{"icon":null,"locationKey":"L2","title":"نوع سیم‌کارت","attributeValueVms":[{"value":"EMERALD","displayText":"زمردی"}],"shortcut":false},{"icon":null,"locationKey":null,"title":"Item Type Id","attributeValueVms":[{"value":"3004","displayText":"3004"}],"shortcut":false},{"icon":null,"locationKey":"L1","title":"دائمی یا اعتباری","attributeValueVms":[{"value":"POSTPAID","displayText":"دائمی"}],"shortcut":false},{"icon":null,"locationKey":null,"title":"قیمت","attributeValueVms":[{"value":"1668000","displayText":"1668000"}],"shortcut":false},{"icon":null,"locationKey":null,"title":"offerId","attributeValueVms":[{"value":"144","displayText":"144"}],"shortcut":false}],"createdOn":"2025-09-09T21:31:04.925"}],"pageNo":155,"pageSize":16,"totalElements":2522,"totalPages":158,"isLast":false}
